azure_smtp_relay/__init__.py
azure_smtp_relay/__main__.py
azure_smtp_relay/address_list.py
azure_smtp_relay/config.py
azure_smtp_relay/handler.py
azure_smtp_relay/relay.py
azure_smtp_relay/toml_config_mgr.py
azure_smtp_relay-1.0.11.dist-info/licenses/LICENSE
azure_smtp_relay-1.0.11.dist-info/METADATA
azure_smtp_relay-1.0.11.dist-info/WHEEL
azure_smtp_relay-1.0.11.dist-info/top_level.txt
azure_smtp_relay-1.0.11.dist-info/RECORD
